agritechtz_cli/__init__.py
agritechtz_pycli-1.0.5.dist-info/LICENSE
agritechtz_pycli-1.0.5.dist-info/METADATA
agritechtz_pycli-1.0.5.dist-info/WHEEL
agritechtz_pycli-1.0.5.dist-info/top_level.txt
agritechtz_pycli-1.0.5.dist-info/RECORD
