Metadata-Version: 2.1
Name: agritechtz-pycli
Version: 1.0.5
Summary: A client library for fetching and processing crop price data in Tanzania.
Home-page: https://github.com/cloudnuttz/agritechtz.git
Author: Moses Kabungo
Author-email: mose.kabungo@gmail.com
License: MIT
Project-URL: Documentation, https://github.com/cloudnuttz/agritechtz.git#readme
Project-URL: Source, https://github.com/cloudnuttz/agritechtz.git
Project-URL: Tracker, https://github.com/cloudnuttz/agritechtz.git/issues
Classifier: Development Status :: 4 - Beta
Classifier: Intended Audience :: Developers
Classifier: License :: OSI Approved :: MIT License
Classifier: Programming Language :: Python :: 3
Classifier: Programming Language :: Python :: 3.11
Classifier: Topic :: Software Development :: Libraries
Classifier: Topic :: Scientific/Engineering :: Information Analysis
Requires-Python: >=3.8
License-File: LICENSE
Requires-Dist: pandas>=1.0.0
Requires-Dist: requests>=2.0.0
Requires-Dist: tqdm>=4.0.0
